reposcope/__init__.py
reposcope/__main__.py
reposcope/cli.py
reposcope/core.py
reposcope/profiles.py
reposcope-0.3.4.dist-info/METADATA
reposcope-0.3.4.dist-info/WHEEL
reposcope-0.3.4.dist-info/entry_points.txt
reposcope-0.3.4.dist-info/licenses/LICENSE
reposcope-0.3.4.dist-info/RECORD
