Metadata-Version: 2.4
Name: reposcope
Version: 0.3.4
Summary: Collect repository files into a single document for easy sharing with AI assistants
Project-URL: Homepage, https://github.com/AlekseiShevkoplias/reposcope
Project-URL: Bug Tracker, https://github.com/AlekseiShevkoplias/reposcope/issues
Project-URL: Repository, https://github.com/AlekseiShevkoplias/reposcope.git
Author-email: AlekseiShevkoplias <shevshelles@gmail.com>
License-File: LICENSE
Classifier: Development Status :: 3 - Alpha
Classifier: Intended Audience :: Developers
Classifier: License :: OSI Approved :: MIT License
Classifier: Operating System :: POSIX :: Linux
Classifier: Programming Language :: Python :: 3
Classifier: Programming Language :: Python :: 3.9
Classifier: Programming Language :: Python :: 3.10
Classifier: Programming Language :: Python :: 3.11
Classifier: Programming Language :: Python :: 3.12
Classifier: Topic :: Software Development :: Libraries :: Python Modules
Requires-Python: >=3.9
Provides-Extra: dev
Requires-Dist: pytest-cov>=6.0.0; extra == 'dev'
Requires-Dist: pytest>=8.3.4; extra == 'dev'
Requires-Dist: ruff>=0.9.3; extra == 'dev'
